setup.py
test/test_model_data.py
test/test_routes.py
topmodel/__init__.py
topmodel/file_system.py
topmodel/hmetrics.py
topmodel/model_data.py
topmodel/plot_helpers.py
topmodel/plots.py
topmodel/settings.py
topmodel.egg-info/PKG-INFO
topmodel.egg-info/SOURCES.txt
topmodel.egg-info/dependency_links.txt
topmodel.egg-info/requires.txt
topmodel.egg-info/top_level.txt