Metadata-Version: 1.0
Name: topmodel
Version: 0.1.1
Summary: Model evaluation
Home-page: UNKNOWN
Author: Julia Evans
Author-email: julia@stripe.com
License: UNKNOWN
Platform: UNKNOWN
